{"cameraMode":{"drawMode":0,"name":"Shaded","section":"Shading Mode"},"sceneLighting":false,"audioPlay":false,"sceneViewState":{"m_AlwaysRefresh":false,"showFog":true,"showSkybox":false,"showFlares":true,"showImageEffects":true,"showParticleSystems":true,"showVisualEffectGraphs":true,"m_FxEnabled":true},"in2DMode":false,"pivot":{"x":-98.31987762451172,"y":-341.7477111816406,"z":139.60836791992188},"rotation":{"x":-0.2020660787820816,"y":0.7081931233406067,"z":-0.22420912981033326,"w":-0.6382511854171753},"size":906.3766479492188,"orthographic":false}